sendspy.py
sendspy-1.0.2.dist-info/METADATA
sendspy-1.0.2.dist-info/WHEEL
sendspy-1.0.2.dist-info/top_level.txt
sendspy-1.0.2.dist-info/RECORD
