Metadata-Version: 2.4
Name: sendspy
Version: 1.0.2
Summary: مكتبة ارسال رسائل تليجرام بسيطة المطور جعفر  @hhvvm5
Home-page: https://github.com/HHVVM1/sendpy
Author: JA3FR
Author-email: hhvvm5@gmail.com
Requires-Dist: requests>=2.25.0
Dynamic: author
Dynamic: author-email
Dynamic: description
Dynamic: description-content-type
Dynamic: home-page
Dynamic: requires-dist
Dynamic: summary
